cross_framework_hpo/__init__.py
cross_framework_hpo/base_pytorch_model.py
cross_framework_hpo/base_tensorflow_model.py
cross_framework_hpo/parameter_sweep.py
cross_framework_hpo/densenet121/__init__.py
cross_framework_hpo/densenet121/pt_densenet.py
cross_framework_hpo/densenet121/tf_densenet.py
cross_framework_hpo/resnet50/__init__.py
cross_framework_hpo/resnet50/pt_resnet.py
cross_framework_hpo/resnet50/tf_resnet.py
cross_framework_hpo/vgg16/__init__.py
cross_framework_hpo/vgg16/pt_vgg.py
cross_framework_hpo/vgg16/tf_vgg.py
cross_framework_hpo/vgg16/updated_torchvision_vgg.py
cross_framework_hpo-0.0.1.dist-info/METADATA
cross_framework_hpo-0.0.1.dist-info/WHEEL
cross_framework_hpo-0.0.1.dist-info/top_level.txt
cross_framework_hpo-0.0.1.dist-info/RECORD
