Metadata-Version: 2.1
Name: cross-framework-hpo
Version: 0.0.1
Summary: Hyperparameter Search tools in order to quantify differences between deep learning frameworks
Home-page: https://github.com/maxzvyagin/cross_framework_hpo
Author: Max Zvyagin
Author-email: max.zvyagin7@gmail.com
License: MIT
Platform: UNKNOWN
Classifier: Development Status :: 4 - Beta
Classifier: License :: OSI Approved :: MIT License
Classifier: Programming Language :: Python
Classifier: Programming Language :: Python :: 3.5
Classifier: Programming Language :: Python :: 3.6
Classifier: Programming Language :: Python :: 3.8
Classifier: Topic :: Software Development :: Libraries
Classifier: Topic :: Software Development :: Libraries :: Python Modules
Classifier: Intended Audience :: Developers
Requires-Python: >=3.5
Requires-Dist: spaceray
Requires-Dist: torch
Requires-Dist: pytorch-lightning
Requires-Dist: tensorflow
Requires-Dist: wandb
